{
	"configurations" : 
	[
		{
			"directories" : 
			[
				{
					"build" : ".",
					"minimumCMakeVersion" : 
					{
						"string" : "3.20"
					},
					"projectIndex" : 0,
					"source" : ".",
					"targetIndexes" : 
					[
						0
					]
				}
			],
			"name" : "Debug",
			"projects" : 
			[
				{
					"directoryIndexes" : 
					[
						0
					],
					"name" : "Lab2_queue",
					"targetIndexes" : 
					[
						0
					]
				}
			],
			"targets" : 
			[
				{
					"directoryIndex" : 0,
					"id" : "Lab2_queue::@6890427a1f51a3e7e1df",
					"jsonFile" : "target-Lab2_queue-Debug-9e64e881c8c5456fd3d6.json",
					"name" : "Lab2_queue",
					"projectIndex" : 0
				}
			]
		}
	],
	"kind" : "codemodel",
	"paths" : 
	{
		"build" : "/Users/i3artek/Studies/Clion_/ADS_Algorithms/Lab2_queue/cmake-build-debug",
		"source" : "/Users/i3artek/Studies/Clion_/ADS_Algorithms/Lab2_queue"
	},
	"version" : 
	{
		"major" : 2,
		"minor" : 2
	}
}
